flamingo/__init__.py
flamingo/api.py
flamingo/app.py
flamingo/build_pack.py
flamingo/dependency.py
flamingo/env.py
flamingo/info.py
flamingo/main.py
flamingo/tools.py
flamingo_cli-1.3.2.dist-info/entry_points.txt
flamingo_cli-1.3.2.dist-info/WHEEL
flamingo_cli-1.3.2.dist-info/METADATA
flamingo_cli-1.3.2.dist-info/RECORD
