Metadata-Version: 2.1
Name: flamingo-cli
Version: 1.3.2
Summary: Flamingo Command Line Interface
Author: Joao Daher
Author-email: joao@daher.dev
Requires-Python: >=3.7,<3.11
Classifier: Programming Language :: Python :: 3
Classifier: Programming Language :: Python :: 3.10
Classifier: Programming Language :: Python :: 3.7
Classifier: Programming Language :: Python :: 3.8
Classifier: Programming Language :: Python :: 3.9
Requires-Dist: click
Requires-Dist: coverage
Requires-Dist: pylint
Requires-Dist: requests
Requires-Dist: tabulate
